aws_pysdk/__init__.py
aws_pysdk/lambda_module.py
aws_pysdk/s3.py
aws_pysdk/session.py
aws_pysdk/ssm.py
actvalue_aws_pysdk-1.0.1.dist-info/METADATA
actvalue_aws_pysdk-1.0.1.dist-info/WHEEL
actvalue_aws_pysdk-1.0.1.dist-info/licenses/LICENSE
actvalue_aws_pysdk-1.0.1.dist-info/RECORD
