Metadata-Version: 2.4
Name: actvalue.aws-pysdk
Version: 1.0.1
Summary: AWS Python SDK wrapper for boto3 commonly used functions
Author: ActValue
License: MIT
License-File: LICENSE
Classifier: License :: OSI Approved :: MIT License
Classifier: Operating System :: OS Independent
Classifier: Programming Language :: Python :: 3
Classifier: Programming Language :: Python :: 3.11
Classifier: Programming Language :: Python :: 3.12
Classifier: Programming Language :: Python :: 3.13
Classifier: Programming Language :: Python :: 3.14
Requires-Python: >=3.11
Requires-Dist: aws-lambda-powertools>=3.23.0
Requires-Dist: boto3>=1.40.0
Provides-Extra: dev
Requires-Dist: pytest>=8.3.4; extra == 'dev'
Requires-Dist: ruff>=0.8.4; extra == 'dev'
Requires-Dist: twine>=6.0.1; extra == 'dev'
